{
  "$schema": "https://biomejs.dev/schemas/1.9.4/schema.json",
  "files": {
    "ignoreUnknown": false,
    "ignore": [
      "**/node_modules",
      "**/public",
      "**/dist",
      ".next",
      ".astro",
      ".github",
      ".vercel",
      ".netlify",
      "pnpm-lock.yaml",
      "bun.lock"
    ]
  },
  "formatter": {
    "enabled": true,
    "indentStyle": "space",
    "indentWidth": 2,
    "lineEnding": "lf",
    "lineWidth": 80
  },
  "linter": {
    "enabled": true,
    "rules": {
      "recommended": true,
      "suspicious": {
        "noExplicitAny": "warn"
      },
      "correctness": {
        "useExhaustiveDependencies": "warn",
        "noUnknownMediaFeatureName": "off"
      },
      "a11y": {
        "useKeyWithClickEvents": "warn",
        "useValidAnchor": "warn"
      },
      "style": {
        "noNonNullAssertion": "off",
        "noUnusedTemplateLiteral": "off"
      }
    }
  },
  "organizeImports": {
    "enabled": true
  },
  "css": {
    "formatter": {
      "enabled": true,
      "indentStyle": "space",
      "indentWidth": 2
    },
    "linter": {
      "enabled": true
    },
    "parser": {
      "cssModules": true
    }
  },
  "javascript": {
    "formatter": {
      "quoteStyle": "single",
      "trailingCommas": "es5"
    }
  },
  "json": {
    "parser": {
      "allowComments": true
    }
  }
}
